https_everywhere/__init__.py
https_everywhere/_chrome_preload_hsts.py
https_everywhere/_fetch.py
https_everywhere/_fixme.py
https_everywhere/_rules.py
https_everywhere/_unregex.py
https_everywhere/_util.py
https_everywhere/adapter.py
https_everywhere/session.py
https_everywhere-0.2.2.dist-info/LICENSE
https_everywhere-0.2.2.dist-info/METADATA
https_everywhere-0.2.2.dist-info/WHEEL
https_everywhere-0.2.2.dist-info/top_level.txt
https_everywhere-0.2.2.dist-info/version.txt
https_everywhere-0.2.2.dist-info/RECORD
